procfs_sensor/__init__.py
procfs_sensor/__main__.py
procfs_sensor-0.1.0.dist-info/LICENSE
procfs_sensor-0.1.0.dist-info/METADATA
procfs_sensor-0.1.0.dist-info/WHEEL
procfs_sensor-0.1.0.dist-info/top_level.txt
procfs_sensor-0.1.0.dist-info/RECORD
