Metadata-Version: 2.1
Name: procfs-sensor
Version: 0.1.0
Summary: Procfs-Sensor is a sensor that monitor CPU usage of cgroup
Home-page: UNKNOWN
Author: Lauric Desauw
License: MIT
Keywords: energy,powerapi,containers,sensor
Platform: UNKNOWN
Classifier: Programming Language :: Python :: 3.7
Classifier: License :: OSI Approved :: GNU Affero General Public License v3
Requires-Python: >=3.7
